readnext/__init__.py
readnext/_modidx.py
readnext/arxiv_categories.py
readnext/arxiv_sync.py
readnext/embedding.py
readnext/main.py
readnext/personalize.py
readnext-0.0.6.dist-info/LICENSE
readnext-0.0.6.dist-info/METADATA
readnext-0.0.6.dist-info/WHEEL
readnext-0.0.6.dist-info/entry_points.txt
readnext-0.0.6.dist-info/top_level.txt
readnext-0.0.6.dist-info/RECORD
