Metadata-Version: 2.1
Name: readnext
Version: 0.0.6
Summary: ReadNext suggests the best papers for you to read next from the ArXiv.
Home-page: https://github.com/fgiasson/ReadNext
Author: Frederick Giasson
Author-email: Frederick Giasson <fred@fgiasson.com>
License: GNU GPLv3
Project-URL: Homepage, https://github.com/fgiasson/readnext
Project-URL: Bug Tracker, https://github.com/fgiasson/readnext/issues
Keywords: nbdev jupyter notebook python
Classifier: Programming Language :: Python :: 3
Classifier: Operating System :: OS Independent
Requires-Python: >=3.7
License-File: LICENSE
Requires-Dist: arxiv
Requires-Dist: cohere
Requires-Dist: pypdf
Requires-Dist: pyzotero
Requires-Dist: typer[all]
Requires-Dist: nameparser
Requires-Dist: python-dotenv
Requires-Dist: chromadb >=0.4.0
Requires-Dist: transformers
Requires-Dist: torch
Requires-Dist: pycryptodome
Provides-Extra: dev
